rebecca.annotationmapper-0.1-py3.4-nspkg.pth
rebecca/annotationmapper/annotations.py
rebecca/annotationmapper/mappers.py
rebecca/annotationmapper/__init__.py
rebecca/annotationmapper/tests/test_mappers.py
rebecca/annotationmapper/tests/__init__.py
rebecca.annotationmapper-0.1.dist-info/DESCRIPTION.rst
rebecca.annotationmapper-0.1.dist-info/METADATA
rebecca.annotationmapper-0.1.dist-info/metadata.json
rebecca.annotationmapper-0.1.dist-info/namespace_packages.txt
rebecca.annotationmapper-0.1.dist-info/RECORD
rebecca.annotationmapper-0.1.dist-info/top_level.txt
rebecca.annotationmapper-0.1.dist-info/WHEEL
