Metadata-Version: 2.0
Name: rebecca.annotationmapper
Version: 0.1
Summary: annotation view mapper for pyramid
Home-page: https://github.com/rebeccaframework/rebecca.annotationmapper
Author: Atsushi Odagiri
Author-email: aodagx@gmail.com
License: MIT
Platform: UNKNOWN
Classifier: Development Status :: 3 - Alpha
Classifier: Framework :: Pyramid
Classifier: License :: OSI Approved :: MIT License
Classifier: Programming Language :: Python :: 3 :: Only
Requires-Dist: pyramid (>=1.6dev)
Requires-Dist: zope.interface
